pyezviz/__init__.py
pyezviz/__main__.py
pyezviz/api_endpoints.py
pyezviz/camera.py
pyezviz/cas.py
pyezviz/client.py
pyezviz/constants.py
pyezviz/exceptions.py
pyezviz/mqtt.py
pyezviz/test_cam_rtsp.py
pyezviz/utils.py
pyezviz-0.2.2.2.dist-info/LICENSE.md
pyezviz-0.2.2.2.dist-info/METADATA
pyezviz-0.2.2.2.dist-info/WHEEL
pyezviz-0.2.2.2.dist-info/entry_points.txt
pyezviz-0.2.2.2.dist-info/top_level.txt
pyezviz-0.2.2.2.dist-info/RECORD
