Metadata-Version: 2.1
Name: pyezviz
Version: 0.2.2.2
Summary: Pilot your Ezviz cameras
Home-page: http://github.com/baqs/pyEzviz/
Author: Pierre Ourdouille
Author-email: baqs@users.github.com
License: Apache Software License 2.0
Requires-Python: >=3.6
License-File: LICENSE.md
Requires-Dist: requests
Requires-Dist: pandas
Requires-Dist: paho-mqtt
Requires-Dist: xmltodict
Requires-Dist: pycryptodome
